main.v
module main_module(
    output Y,
    input clk
);
reg [4:0] count=5'b0000;
assign Y=count[4];
always @(posedge clk)
if (count==5'b11111) count<=5'b00000;
else count<=count+5'b00001;
endmodule

t_main.v
`timescale 100ns/100ns
`include "main.v"
module t_main;
wire Y;
reg clk;

main_module M1(Y,clk);

initial begin
    $dumpfile("dump.vcd");
    $dumpvars(0,t_main);
    clk=1'b0;
    #1000 $finish;
end
always #5 clk=(!clk);
endmodule

dump.vcd
$date
	Mon Dec 06 23:07:18 2021
$end
$version
	Icarus Verilog
$end
$timescale
	100ns
$end
$scope module t_main $end
$var wire 1 ! Y $end
$var reg 1 " clk $end
$scope module M1 $end
$var wire 1 " clk $end
$var wire 1 ! Y $end
$var reg 5 # count [4:0] $end
$upscope $end
$upscope $end
$enddefinitions $end
#0
$dumpvars
b0 #
0"
0!
$end
#5
b1 #
1"
#10
0"
#15
b10 #
1"
#20
0"
#25
b11 #
1"
#30
0"
#35
b100 #
1"
#40
0"
#45
b101 #
1"
#50
0"
#55
b110 #
1"
#60
0"
#65
b111 #
1"
#70
0"
#75
b1000 #
1"
#80
0"
#85
b1001 #
1"
#90
0"
#95
b1010 #
1"
#100
0"
#105
b1011 #
1"
#110
0"
#115
b1100 #
1"
#120
0"
#125
b1101 #
1"
#130
0"
#135
b1110 #
1"
#140
0"
#145
b1111 #
1"
#150
0"
#155
1!
b10000 #
1"
#160
0"
#165
b10001 #
1"
#170
0"
#175
b10010 #
1"
#180
0"
#185
b10011 #
1"
#190
0"
#195
b10100 #
1"
#200
0"
#205
b10101 #
1"
#210
0"
#215
b10110 #
1"
#220
0"
#225
b10111 #
1"
#230
0"
#235
b11000 #
1"
#240
0"
#245
b11001 #
1"
#250
0"
#255
b11010 #
1"
#260
0"
#265
b11011 #
1"
#270
0"
#275
b11100 #
1"
#280
0"
#285
b11101 #
1"
#290
0"
#295
b11110 #
1"
#300
0"
#305
b11111 #
1"
#310
0"
#315
0!
b0 #
1"
#320
0"
#325
b1 #
1"
#330
0"
#335
b10 #
1"
#340
0"
#345
b11 #
1"
#350
0"
#355
b100 #
1"
#360
0"
#365
b101 #
1"
#370
0"
#375
b110 #
1"
#380
0"
#385
b111 #
1"
#390
0"
#395
b1000 #
1"
#400
0"
#405
b1001 #
1"
#410
0"
#415
b1010 #
1"
#420
0"
#425
b1011 #
1"
#430
0"
#435
b1100 #
1"
#440
0"
#445
b1101 #
1"
#450
0"
#455
b1110 #
1"
#460
0"
#465
b1111 #
1"
#470
0"
#475
1!
b10000 #
1"
#480
0"
#485
b10001 #
1"
#490
0"
#495
b10010 #
1"
#500
0"
#505
b10011 #
1"
#510
0"
#515
b10100 #
1"
#520
0"
#525
b10101 #
1"
#530
0"
#535
b10110 #
1"
#540
0"
#545
b10111 #
1"
#550
0"
#555
b11000 #
1"
#560
0"
#565
b11001 #
1"
#570
0"
#575
b11010 #
1"
#580
0"
#585
b11011 #
1"
#590
0"
#595
b11100 #
1"
#600
0"
#605
b11101 #
1"
#610
0"
#615
b11110 #
1"
#620
0"
#625
b11111 #
1"
#630
0"
#635
0!
b0 #
1"
#640
0"
#645
b1 #
1"
#650
0"
#655
b10 #
1"
#660
0"
#665
b11 #
1"
#670
0"
#675
b100 #
1"
#680
0"
#685
b101 #
1"
#690
0"
#695
b110 #
1"
#700
0"
#705
b111 #
1"
#710
0"
#715
b1000 #
1"
#720
0"
#725
b1001 #
1"
#730
0"
#735
b1010 #
1"
#740
0"
#745
b1011 #
1"
#750
0"
#755
b1100 #
1"
#760
0"
#765
b1101 #
1"
#770
0"
#775
b1110 #
1"
#780
0"
#785
b1111 #
1"
#790
0"
#795
1!
b10000 #
1"
#800
0"
#805
b10001 #
1"
#810
0"
#815
b10010 #
1"
#820
0"
#825
b10011 #
1"
#830
0"
#835
b10100 #
1"
#840
0"
#845
b10101 #
1"
#850
0"
#855
b10110 #
1"
#860
0"
#865
b10111 #
1"
#870
0"
#875
b11000 #
1"
#880
0"
#885
b11001 #
1"
#890
0"
#895
b11010 #
1"
#900
0"
#905
b11011 #
1"
#910
0"
#915
b11100 #
1"
#920
0"
#925
b11101 #
1"
#930
0"
#935
b11110 #
1"
#940
0"
#945
b11111 #
1"
#950
0"
#955
0!
b0 #
1"
#960
0"
#965
b1 #
1"
#970
0"
#975
b10 #
1"
#980
0"
#985
b11 #
1"
#990
0"
#995
b100 #
1"
